odoo/addons/hr_birthday_welcome_message/README.rst
odoo/addons/hr_birthday_welcome_message/__init__.py
odoo/addons/hr_birthday_welcome_message/__manifest__.py
odoo/addons/hr_birthday_welcome_message/i18n/es.po
odoo/addons/hr_birthday_welcome_message/i18n/hr_birthday_welcome_message.pot
odoo/addons/hr_birthday_welcome_message/i18n/it.po
odoo/addons/hr_birthday_welcome_message/models/__init__.py
odoo/addons/hr_birthday_welcome_message/models/hr_employee.py
odoo/addons/hr_birthday_welcome_message/readme/CONFIGURE.rst
odoo/addons/hr_birthday_welcome_message/readme/CONTRIBUTORS.rst
odoo/addons/hr_birthday_welcome_message/readme/DESCRIPTION.rst
odoo/addons/hr_birthday_welcome_message/readme/USAGE.rst
odoo/addons/hr_birthday_welcome_message/static/description/icon.png
odoo/addons/hr_birthday_welcome_message/static/description/index.html
odoo/addons/hr_birthday_welcome_message/static/src/js/greeting_message.js
odoo/addons/hr_birthday_welcome_message/tests/__init__.py
odoo/addons/hr_birthday_welcome_message/tests/test_hr_birthday_welcome_message.py
odoo_addon_hr_birthday_welcome_message-16.0.1.0.0.2.dist-info/METADATA
odoo_addon_hr_birthday_welcome_message-16.0.1.0.0.2.dist-info/WHEEL
odoo_addon_hr_birthday_welcome_message-16.0.1.0.0.2.dist-info/top_level.txt
odoo_addon_hr_birthday_welcome_message-16.0.1.0.0.2.dist-info/RECORD
